cli_base/__init__.py
cli_base/__main__.py
cli_base/autodiscover.py
cli_base/click_defaults.py
cli_base/constants.py
cli_base/run_pip_audit.py
cli_base/tyro_commands.py
cli_base/cli_app/__init__.py
cli_base/cli_app/shell_completion.py
cli_base/cli_app/update_readme_history.py
cli_base/cli_dev/__init__.py
cli_base/cli_dev/code_style.py
cli_base/cli_dev/packaging.py
cli_base/cli_dev/shell_completion.py
cli_base/cli_dev/testing.py
cli_base/cli_tools/__init__.py
cli_base/cli_tools/code_style.py
cli_base/cli_tools/constants.py
cli_base/cli_tools/dev_tools.py
cli_base/cli_tools/dict_utils.py
cli_base/cli_tools/git.py
cli_base/cli_tools/git_history.py
cli_base/cli_tools/path_utils.py
cli_base/cli_tools/rich_utils.py
cli_base/cli_tools/shell_completion.py
cli_base/cli_tools/string_utils.py
cli_base/cli_tools/subprocess_utils.py
cli_base/cli_tools/verbosity.py
cli_base/cli_tools/version_info.py
cli_base/cli_tools/test_utils/__init__.py
cli_base/cli_tools/test_utils/assertion.py
cli_base/cli_tools/test_utils/base_testcases.py
cli_base/cli_tools/test_utils/cli_readme.py
cli_base/cli_tools/test_utils/environment_fixtures.py
cli_base/cli_tools/test_utils/git_utils.py
cli_base/cli_tools/test_utils/logs.py
cli_base/cli_tools/test_utils/rich_click_test_utils.py
cli_base/cli_tools/test_utils/rich_test_utils.py
cli_base/cli_tools/test_utils/shutil_mocks.py
cli_base/cli_tools/test_utils/snapshot.py
cli_base/cli_tools/test_utils/subprocess_mocks.py
cli_base/cli_tools/test_utils/temp_utils.py
cli_base/cli_tools/tests/__init__.py
cli_base/cli_tools/tests/test_code_style.py
cli_base/cli_tools/tests/test_dev_tools.py
cli_base/cli_tools/tests/test_dict_utils.py
cli_base/cli_tools/tests/test_environ_fixtures.py
cli_base/cli_tools/tests/test_git.py
cli_base/cli_tools/tests/test_git_git_apply_patch_1.snapshot.patch
cli_base/cli_tools/tests/test_git_git_diff_1.snapshot.patch
cli_base/cli_tools/tests/test_git_history.py
cli_base/cli_tools/tests/test_path_utils.py
cli_base_utilities-0.27.3.dist-info/METADATA
cli_base_utilities-0.27.3.dist-info/WHEEL
cli_base_utilities-0.27.3.dist-info/entry_points.txt
cli_base_utilities-0.27.3.dist-info/RECORD
