Metadata-Version: 2.4
Name: cli-base-utilities
Version: 0.27.3
Summary: Helpers to bild a CLI program
Project-URL: Documentation, https://github.com/jedie/cli-base-utilities
Project-URL: Source, https://github.com/jedie/cli-base-utilities
Author-email: Jens Diemer <github@jensdiemer.de>
License: GPL-3.0-or-later
Requires-Python: >=3.11
Requires-Dist: bx-py-utils
Requires-Dist: packaging
Requires-Dist: python-dateutil
Requires-Dist: rich
Requires-Dist: tomlkit
Requires-Dist: tyro
